[
    {
      "id": "app001",
      "name": "CodeCraft Junior",
      "developer": "BrightByte Labs",
      "thumbnail": "https://encrypted-tbn0.gstatic.com/images?q=tbn:ANd9GcTPUKfHmKe2MSadOe0xDCzq90w_kI3V8Bo3OQ&s",
      "banner": "https://www.brains-and-motion.com/cdn/shop/files/codecraft-junior-digital-discoveries-with-scratchjr-395051.png?v=1724441058",
      "downloads": 1200000,
      "category": "Education",
      "rating": 4.6,
      "description": "Learn to code through fun challenges and storytelling! Perfect for kids and beginners.",
      "features": [
        "Drag-and-drop coding",
        "Colorful animated lessons",
        "Daily practice quests"
      ],
      "reviews": [
        {
          "user": "future_dev33",
          "rating": 5,
          "comment": "This app got my niece into coding—highly recommended!"
        }
      ]
    },
    {
      "id": "app002",
      "name": "FocusNest",
      "developer": "NeuraSoft Studios",
      "thumbnail": "https://encrypted-tbn0.gstatic.com/images?q=tbn:ANd9GcRkgnDY1mhi1F0ab8mXnav6aZrUqZfa0_lDwQ&s",
      "banner": "https://encrypted-tbn0.gstatic.com/images?q=tbn:ANd9GcQPQz7q3h78_kPxM23BHvxz7JoKz__CrZeFgA&s",
      "downloads": 850000,
      "category": "Productivity",
      "rating": 4.5,
      "description": "Minimalist focus timer that helps you stay productive using the Pomodoro technique.",
      "features": [
        "Custom timer sessions",
        "Distraction blocking mode",
        "Focus analytics"
      ],
      "reviews": [
        {
          "user": "zenworker",
          "rating": 4,
          "comment": "Clean UI, works great. Would love some background sounds though."
        }
      ]
    },
    {
      "id": "app003",
      "name": "Galaxy Clash VR",
      "developer": "NovaPixel Games",
      "thumbnail": "https://encrypted-tbn0.gstatic.com/images?q=tbn:ANd9GcTt1j3wtBqWZ0eDg82MhURxLQ1pYXxt8AbcGA&s",
      "banner": "https://encrypted-tbn0.gstatic.com/images?q=tbn:ANd9GcQgnwUJ5T-Hcsp7Dz38bRtqVDl25JCCmrUnYg&s",
      "downloads": 500000,
      "category": "Gaming",
      "rating": 4.7,
      "description": "Strap in for a 3D space dogfight experience in VR. Pilot your ship, shoot down enemies, and explore galaxies.",
      "features": [
        "Immersive VR combat",
        "Upgradeable ships",
        "Multiplayer mode"
      ],
      "reviews": [
        {
          "user": "astro_gunner",
          "rating": 5,
          "comment": "Feels like Star Wars with better controls—love it!"
        }
      ]
    },
    {
      "id": "app004",
      "name": "NoteFluent",
      "developer": "SwiftThink Devs",
      "thumbnail": "https://lh6.googleusercontent.com/proxy/kmSfi2OJ-QsClrEJGNKUo3IZtoEzbcx4G7pw2qSZe7ZT42vVNE8Rc4P6RZlTevuhyYjRguFdbWmtyTTcmJ_E8sZ5amIJITVZYvLFbOMC-HirCj1tj2BWI51rZM1o",
      "banner": "https://static-00.iconduck.com/assets.00/note-taking-app-icon-2048x2048-mt93xtc5.png",
      "downloads": 2000000,
      "category": "Productivity",
      "rating": 4.2,
      "description": "Elegant note-taking app with markdown support and cloud sync. Stay organized and creative.",
      "features": [
        "Markdown editing",
        "Offline mode",
        "Cross-device sync"
      ],
      "reviews": [
        {
          "user": "notegeek92",
          "rating": 4,
          "comment": "Great for writing blog drafts. A little laggy on old phones."
        }
      ]
    },
    {
      "id": "app005",
      "name": "Learnify Math",
      "developer": "SmartWhiz Inc.",
      "thumbnail": "https://encrypted-tbn0.gstatic.com/images?q=tbn:ANd9GcSxdVLrTc6RxoHmb0NqD0j_x_LRU_HClgs5-Q&s",
      "banner": "https://encrypted-tbn0.gstatic.com/images?q=tbn:ANd9GcTed28_SX6KLC1XLyZlWxvzkW7wKfjQBFlyig&s",
      "downloads": 980000,
      "category": "Education",
      "rating": 4.3,
      "description": "Interactive math lessons, quizzes, and puzzles for students from Grade 1 to 10.",
      "features": [
        "Level-based learning",
        "Live progress tracking",
        "Animated explanations"
      ],
      "reviews": [
        {
          "user": "mathmaster88",
          "rating": 5,
          "comment": "My son actually looks forward to math now. Awesome!"
        }
      ]
    },
    {
      "id": "app006",
      "name": "Pixel Siege: Warzone",
      "developer": "RedBear Studio",
      "thumbnail": "https://encrypted-tbn0.gstatic.com/images?q=tbn:ANd9GcSBOq67s-JdD64Iye43DLoonkaTdEVN0IIALg&s",
      "banner": "https://encrypted-tbn0.gstatic.com/images?q=tbn:ANd9GcRvlFpMhs_u5MMhdqrrAylW86oXBmnT0KFMUw&s",
      "downloads": 1500000,
      "category": "Gaming",
      "rating": 4.1,
      "description": "Retro-style shooter game with team-based multiplayer action. Fast-paced and addictive!",
      "features": [
        "Online team battles",
        "Weapon customization",
        "Ranked mode"
      ],
      "reviews": [
        {
          "user": "sniperboi21",
          "rating": 4,
          "comment": "Love the pixel graphics! Just wish there were more maps."
        }
      ]
    },
    {
      "id": "app007",
      "name": "MindVault",
      "developer": "NeuroNova Tech",
      "thumbnail": "https://www.classcentral.com/report/wp-content/uploads/2023/06/BCG-Banner-Neuroscience.png",
      "banner": "https://thumbs.dreamstime.com/b/innovative-digital-brain-logo-design-futuristic-symbol-ai-machine-learning-neuroscience-startups-captivating-351857685.jpg",
      "downloads": 720000,
      "category": "Education",
      "rating": 4.6,
      "description": "A neuroscience-based learning tool to improve memory, focus, and critical thinking.",
      "features": [
        "Memory games",
        "Daily brain challenges",
        "Progress visualization"
      ],
      "reviews": [
        {
          "user": "focusfan",
          "rating": 5,
          "comment": "This app helped me improve concentration during exams!"
        }
      ]
    },
    {
      "id": "app008",
      "name": "TaskBloom",
      "developer": "Bloomware Co.",
      "thumbnail": "https://encrypted-tbn0.gstatic.com/images?q=tbn:ANd9GcQ78ghacKkNyK5ZZwlRseXjRxm8fyn2sJ5akw&s",
      "banner": "https://i.pinimg.com/736x/f8/98/bf/f898bfb34a80f0784e1417c86a096e13.jpg",
      "downloads": 3100000,
      "category": "Productivity",
      "rating": 4.9,
      "description": "A beautiful to-do app that combines task management with habit tracking.",
      "features": [
        "Daily habit streaks",
        "Task reminders",
        "Beautiful themes"
      ],
      "reviews": [
        {
          "user": "planqueen",
          "rating": 5,
          "comment": "The only planner I’ve consistently used every day. It’s gorgeous and functional!"
        }
      ]
    }
  ]
  